context_logger_wrapper/__init__.py
context_logger_wrapper-0.0.1.dist-info/licenses/LICENSE
context_logger_wrapper-0.0.1.dist-info/METADATA
context_logger_wrapper-0.0.1.dist-info/WHEEL
context_logger_wrapper-0.0.1.dist-info/top_level.txt
context_logger_wrapper-0.0.1.dist-info/RECORD
