Metadata-Version: 2.4
Name: context_logger_wrapper
Version: 0.0.1
Summary: Context Logger Wrapper
Home-page: https://github.com/maximz/context-logger-wrapper
Author: Maxim Zaslavsky
Author-email: maxim@maximz.com
License: MIT license
Classifier: Development Status :: 2 - Pre-Alpha
Classifier: Intended Audience :: Developers
Classifier: License :: OSI Approved :: MIT License
Classifier: Natural Language :: English
Classifier: Programming Language :: Python :: 3
Classifier: Programming Language :: Python :: 3.8
Classifier: Programming Language :: Python :: 3.9
Requires-Python: >=3.8
License-File: LICENSE
Requires-Dist: log-with-context
Requires-Dist: extendanything
Dynamic: author
Dynamic: author-email
Dynamic: classifier
Dynamic: description
Dynamic: description-content-type
Dynamic: home-page
Dynamic: license
Dynamic: license-file
Dynamic: requires-dist
Dynamic: requires-python
Dynamic: summary
